Metadata-Version: 2.4
Name: sonia-barrera-sdk
Version: 3.0.1
Summary: Vel dolores harum ip
Author-email: Zahra naseem <kawanyqum@mailinator.com>
Project-URL: Documentation, https://documentation.com
Requires-Python: >=3.7
License-File: LICENSE
Requires-Dist: apimatic-core>=0.2.22,~=0.2.0
Requires-Dist: apimatic-core-interfaces>=0.1.5,~=0.1.0
Requires-Dist: apimatic-requests-client-adapter>=0.1.8,~=0.1.0
Provides-Extra: testutils
Requires-Dist: pytest>=7.2.2; extra == "testutils"
Dynamic: license-file
